<?xml version="1.0" encoding="utf-8"?>
<ModMetaData>
	<name>Anima Bionics - Forked [RUS]</name>
	<author>TzverG</author>
	<supportedVersions>
		<li>1.4</li>
	</supportedVersions>
	<packageId>TzverG.Seti.Victor.AnimaBodies.Ru</packageId>
	<description>Это НЕ ОБЫЧНЫЙ перевод модификации от авторов Seti, Magenta_Ivy и Victor для личного пользования. Перевод основан на работе автора Kamikadza13, но он ОСНОВАТЕЛЬНО переработан. \n\nОригинальное описание:\nВыращивайте анима части тела, будьте едины с природой, вживляйте в свое тело анима-дриад.\n\nВАЖНОЕ ЗАМЕЧАНИЕ ОТ ЛОКАЛИЗАТОРА:\nЭто тестовая версия перевода, созданная в первую очередь для себя, а во вторую - для моих подписчиков. Перевод не просто вольный, здесь придумана некая концепция, позволяющая наполнить смыслом некоторые, нарочито упрощённые разработчиком модификации, моменты. Каждому, добавленному модификацией модулю в описание добавлен АВТОРСКИЙ текст вашего покорного слуги, для тех кто в танке - это означает что автор модификации подобного не писал и не планировал. Возможно разработчик решил оставить продумывание деталей на конечного потребителя своего интелектуального труда, но конкретно в данном случае я взял на себя смелость сделать это за вас. Надеюсь вам понравится, в конечном счёте это всего-лишь перевод, никаких параметров я не менял и не трогал и в худшем случае вы просто можете не читать описания как делает большинство игроков.\n\nВ случае если владельцу модификации не понравится подобное коверкание его первоначальной идеи, прошу связаться со мной в ЛС, и я уберу данное творчество из публичного доступа. \n\nС уважением, ваш локализатор TzverG.</description>
	<modDependencies>
		<li>
			<packageId>Seti.Victor.AnimaBodies</packageId>
			<displayName>Anima Bionics - Forked</displayName>
			<steamWorkshopUrl>https://steamcommunity.com/sharedfiles/filedetails/?id=2879835262</steamWorkshopUrl>
		</li>
	</modDependencies>
	<loadAfter>
		<li>Seti.Victor.AnimaBodies</li>
	</loadAfter>
</ModMetaData>